odoo9_addon_l10n_ar_base_country_state-9.0.1.0.0-py2.7-nspkg.pth
odoo_addons/l10n_ar_base_country_state/README.md
odoo_addons/l10n_ar_base_country_state/__openerp__.py
odoo_addons/l10n_ar_base_country_state/country_state_data.xml
odoo_addons/l10n_ar_base_country_state/__init__.py
odoo_addons/l10n_ar_base_country_state/AUTHORS
odoo_addons/l10n_ar_base_country_state/static/description/icon.png
odoo9_addon_l10n_ar_base_country_state-9.0.1.0.0.dist-info/top_level.txt
odoo9_addon_l10n_ar_base_country_state-9.0.1.0.0.dist-info/WHEEL
odoo9_addon_l10n_ar_base_country_state-9.0.1.0.0.dist-info/RECORD
odoo9_addon_l10n_ar_base_country_state-9.0.1.0.0.dist-info/metadata.json
odoo9_addon_l10n_ar_base_country_state-9.0.1.0.0.dist-info/DESCRIPTION.rst
odoo9_addon_l10n_ar_base_country_state-9.0.1.0.0.dist-info/METADATA
odoo9_addon_l10n_ar_base_country_state-9.0.1.0.0.dist-info/namespace_packages.txt
