Metadata-Version: 2.0
Name: odoo9-addon-l10n-ar-base-country-state
Version: 9.0.1.0.0
Summary: Base Argentina's States (aka Provinces)
Home-page: UNKNOWN
Author: UNKNOWN
Author-email: UNKNOWN
License: UNKNOWN
Platform: UNKNOWN
Requires-Dist: odoo (<9.1a,>=9.0a)
Classifier: Programming Language :: Python :: 2.7
Classifier: Framework :: Odoo
